roboclaw/__init__.py
roboclaw/roboclaw.py
roboclaw/roboclaw_cmd.py
roboclaw-1.0.0.dev1.dist-info/DESCRIPTION.rst
roboclaw-1.0.0.dev1.dist-info/METADATA
roboclaw-1.0.0.dev1.dist-info/RECORD
roboclaw-1.0.0.dev1.dist-info/WHEEL
roboclaw-1.0.0.dev1.dist-info/metadata.json
roboclaw-1.0.0.dev1.dist-info/top_level.txt
