Metadata-Version: 1.1
Name: roboclaw
Version: 1.0.0.dev1
Summary: Unofficial python library for talking to RoboClaw motor controllers
Home-page: https://github.com/urill/pyroboclaw
Author: Keshuai Xu and Ben Gillette
Author-email: urillx@gmail.com
License: MIT
Keywords: pololu roboclaw motor
Platform: UNKNOWN
Classifier: Development Status :: 3 - Alpha
Classifier: Intended Audience :: Developers
Classifier: Topic :: Scientific/Engineering :: Interface Engine/Protocol Translator
Classifier: License :: OSI Approved :: MIT License
Classifier: Programming Language :: Python :: 3
Classifier: Programming Language :: Python :: 3.5
Classifier: Programming Language :: Python :: 3.6
